pybox/__init__.py
pybox/pyber.py
pywest-1.0.0.dist-info/licenses/LICENSE
pywest-1.0.0.dist-info/METADATA
pywest-1.0.0.dist-info/WHEEL
pywest-1.0.0.dist-info/entry_points.txt
pywest-1.0.0.dist-info/top_level.txt
pywest-1.0.0.dist-info/RECORD
