Metadata-Version: 2.4
Name: pywest
Version: 1.0.0
Summary: pybox - No Code Obfuscation, No Compiled PYCs, Open Python Projects
Author-email: pybox Community <community@pybox.dev>
License: MIT
Project-URL: Homepage, https://github.com/pybox-community/pybox
Project-URL: Documentation, https://pybox.dev/docs
Project-URL: Repository, https://github.com/pybox-community/pybox.git
Project-URL: Bug Tracker, https://github.com/pybox-community/pybox/issues
Keywords: python,portable,embeddable,development,cli,uv,package-manager
Classifier: Development Status :: 5 - Production/Stable
Classifier: Intended Audience :: Developers
Classifier: License :: OSI Approved :: MIT License
Classifier: Programming Language :: Python :: 3
Classifier: Programming Language :: Python :: 3.8
Classifier: Programming Language :: Python :: 3.9
Classifier: Programming Language :: Python :: 3.10
Classifier: Programming Language :: Python :: 3.11
Classifier: Programming Language :: Python :: 3.12
Classifier: Topic :: Software Development :: Build Tools
Classifier: Topic :: System :: Software Distribution
Classifier: Topic :: Software Development :: Libraries :: Python Modules
Requires-Python: >=3.8
License-File: LICENSE
Requires-Dist: tomli>=1.2.0; python_version < "3.11"
Requires-Dist: tomli-w>=1.0.0
Dynamic: license-file
